{"id":119,"locale":"lo","version":1,"date_added":"1601807442851","source_version":3,"translation":{"title":"ຊ່ວຍ Microsoft ປັບປຸງ","description":"ແບ່ງປັນຂໍ້ມູນກ່ຽວກັບວິທີ ແລະ ສິ່ງທີ່ທ່ານພິມ, ລວມທັງຄວາມຖີ່ ແລະ ການລຽງລຳດັບຂອງຄຳທີ່ທ່ານໃຊ້, ສາມາດຊ່ວຍໃນການພິມຂອງທ່ານ ແລະ ປະສົບການປ້ອນຂໍ້ມູນພາສາອຶ່ນໃນ Microsoft ແອັບ ແລະ ອຸປະກອນອຶ່ນໆ.","question":"ທ່ານຍິນຍອມທີ່ຈະແບ່ງປັນບໍ່?","consent_yes":"ຍິນຍອມ","consent_no":"ບໍ່ຍິນຍອມ","more_details":"ສຳລັບຂໍ້ມູນເພີ່ມຕື່ມ, ກວດໄດ້ທີ່ Microsoft SwiftKey <a href=\"%s$1\">ນະໂຍບາຍຄວາມເປັນສ່ວນຕົວ</a> ແລະ <a href=\"%s$2\">ອ່ານເພີ່ມຕື່ມທີ່</a>","url_learn_more":"https://support.swiftkey.com/hc/en-us/articles/115001737845","url_privacy_policy":"https://go.microsoft.com/fwlink/?LinkId=521839"}}