{"id":73,"locale":"it","version":1,"date_added":"1601807442851","source_version":3,"translation":{"title":"Aiuta Microsoft a migliorare i suoi prodotti e servizi","description":"La condivisione dei dati relativi a come e a cosa digiti, inclusi la frequenza con cui usi determinate parole e il loro ordine, ci aiuta a migliorare le esperienze di digitazione e di inserimento di testo in altre lingue nelle app e nei servizi Microsoft.","question":"Acconsenti alla condivisione?","consent_yes":"Sì","consent_no":"No","more_details":"Per maggiori dettagli, consulta l'<a href=\"%s$1\">Informativa sulla privacy</a> di Microsoft SwiftKey e la pagina <a href=\"%s$2\">Scopri di più</a>","url_learn_more":"https://support.swiftkey.com/hc/it/articles/115001737845","url_privacy_policy":"https://go.microsoft.com/fwlink/?LinkId=521839"}}