{"id":37,"locale":"de","version":1,"date_added":"1601807442851","source_version":3,"translation":{"title":"Tragen Sie zur Verbesserung von Microsoft bei","description":"Das Teilen von Daten darüber, wie und was Sie tippen, einschließlich wie oft Sie gewisse Wörter verwenden und in welcher Reihenfolge, hilft uns dabei, die Eingabe und andere Sprachinput-Erfahrungen bei Microsoft Apps und Services zu verbessern.","question":"Stimmen Sie dem Teilen zu?","consent_yes":"Ja","consent_no":"Nein","more_details":"Für weitere Details, prüfen Sie Microsoft SwiftKey <a href=\"%s$1\">Datenschutzrichtlinie</a> und <a href=\"%s$2\">erfahren Sie mehr</a>","url_learn_more":"https://support.swiftkey.com/hc/de/articles/115001737845","url_privacy_policy":"https://go.microsoft.com/fwlink/?LinkId=521839"}}